Helper.py
metaReport.py
squeezemd-0.9.7.data/data/bin/10_InteractionSurface.py
squeezemd-0.9.7.data/data/bin/11_DissocationAnalysis.py
squeezemd-0.9.7.data/data/bin/12_QTClustering.py
squeezemd-0.9.7.data/data/bin/13_PymolClustering.py
squeezemd-0.9.7.data/data/bin/1_mutation.py
squeezemd-0.9.7.data/data/bin/2_MD.py
squeezemd-0.9.7.data/data/bin/3.1_ExplorativeTrajectoryAnalysis.py
squeezemd-0.9.7.data/data/bin/3.2_Compute_RMSF.py
squeezemd-0.9.7.data/data/bin/3.3_Visualize_RMSF.py
squeezemd-0.9.7.data/data/bin/4_centerMDTraj.py
squeezemd-0.9.7.data/data/bin/5.1_Posco_ExtractLastFrames.py
squeezemd-0.9.7.data/data/bin/5.2_Posco_TransformDF.py
squeezemd-0.9.7.data/data/bin/5.4_Posco_Heatmap.py
squeezemd-0.9.7.data/data/bin/5.5_Posco_Barplot.py
squeezemd-0.9.7.data/data/bin/7_interactionFingerprint.py
squeezemd-0.9.7.data/data/bin/8_GlobalFinterprintAnalysis.py
squeezemd-0.9.7.data/data/bin/9_FreeEnergyStats.py
squeezemd-0.9.7.data/data/bin/Helper.py
squeezemd-0.9.7.data/data/bin/RMSD.rst
squeezemd-0.9.7.data/data/bin/RMSF.rst
squeezemd-0.9.7.data/data/bin/Snakefile
squeezemd-0.9.7.data/data/bin/interaction.rst
squeezemd-0.9.7.data/data/bin/metaReport.py
squeezemd-0.9.7.data/data/bin/posco.rst
squeezemd-0.9.7.data/data/bin/pymol_template.pml
squeezemd-0.9.7.data/data/bin/squeeze
squeezemd-0.9.7.dist-info/licenses/LICENSE
squeezemd-0.9.7.dist-info/METADATA
squeezemd-0.9.7.dist-info/WHEEL
squeezemd-0.9.7.dist-info/entry_points.txt
squeezemd-0.9.7.dist-info/top_level.txt
squeezemd-0.9.7.dist-info/RECORD
