Metadata-Version: 2.4
Name: squeezeMD
Version: 0.9.7
Summary: SqueezeMD is a autmated Molecular dynamics workflow with extensive post-analysis for PPi
Author-email: Rüthemann Peter <peter.ruethemann@gmail.com>
Maintainer-email: peter <peter@gmail.com>
License: MIT
Project-URL: bugs, https://github.com/pruethemann/squeezemd
Project-URL: changelog, https://github.com/pruethemann/ruedi/blob/master/changelog.md
Project-URL: homepage, https://github.com/pruethemann/squeezemd
Requires-Python: >=3.10
License-File: LICENSE
Requires-Dist: typer
Provides-Extra: test
Requires-Dist: coverage; extra == "test"
Requires-Dist: pytest; extra == "test"
Requires-Dist: ruff; extra == "test"
Requires-Dist: ty; extra == "test"
Requires-Dist: ipdb; extra == "test"
Dynamic: license-file
